el/__init__.py
el-0.0.6.dist-info/licenses/LICENSE
el-0.0.6.dist-info/METADATA
el-0.0.6.dist-info/WHEEL
el-0.0.6.dist-info/top_level.txt
el-0.0.6.dist-info/RECORD
