Metadata-Version: 2.4
Name: el
Version: 0.0.6
Summary: Includes functions to manipulate adwords datasets
Home-page: https://github.com/cavart28/el
Author: C Avart
License: apache-2.0
Platform: any
License-File: LICENSE
Dynamic: license-file
